Witsi/DiagramasHD.py
Witsi/__init__.py
Witsi-0.0.5.dist-info/METADATA
Witsi-0.0.5.dist-info/WHEEL
Witsi-0.0.5.dist-info/top_level.txt
Witsi-0.0.5.dist-info/RECORD
