Metadata-Version: 2.1
Name: Witsi
Version: 0.0.5
Summary: Witsi Witsi - Diagramador de mallas
Author: Rodrigo Huerta García <rodrigo.huerta.garcia@bbva.com>,
Author-email: <andreafernanda.muniz@bbva.com>
Keywords: python,Witsi Wisti
Classifier: Development Status :: 3 - Alpha
Classifier: Intended Audience :: Education
Classifier: Programming Language :: Python :: 2
Classifier: Programming Language :: Python :: 3
Classifier: Operating System :: MacOS :: MacOS X
Classifier: Operating System :: Microsoft :: Windows
Requires-Dist: requests
Requires-Dist: pandas
Requires-Dist: matplotlib
Requires-Dist: networkx
Requires-Dist: graphviz
